semi_secret/__init__.py
semi_secret/cli.py
semi_secret/crypto.py
semi_secret/storage.py
semi_secret/assets/example.txt
semi_secret-1.0.4.dist-info/LICENSE
semi_secret-1.0.4.dist-info/METADATA
semi_secret-1.0.4.dist-info/WHEEL
semi_secret-1.0.4.dist-info/entry_points.txt
semi_secret-1.0.4.dist-info/top_level.txt
semi_secret-1.0.4.dist-info/RECORD
