Metadata-Version: 2.1
Name: semi_secret
Version: 1.0.4
Summary: Semi Secret Key-value storage
Home-page: https://github.com/zackees/semi-secret
Maintainer: Zachary Vorhies
License: BSD 3-Clause License
Keywords: template-python-cmd
Classifier: Programming Language :: Python :: 3
Requires-Python: >=3.7
License-File: LICENSE
Requires-Dist: cryptography>=3.4.7
Requires-Dist: appdirs>=1.4.4
Provides-Extra: dev
Requires-Dist: black; extra == "dev"
Requires-Dist: isort; extra == "dev"
Requires-Dist: mypy; extra == "dev"
Requires-Dist: pytest; extra == "dev"
Requires-Dist: tox; extra == "dev"
Requires-Dist: ruff; extra == "dev"
Requires-Dist: pytest-xdist; extra == "dev"
